arxiv_mcp/__init__.py
arxiv_mcp/app.py
arxiv_mcp/server.py
arxiv_mcp/utils.py
arxiv_mcp/prompts/__init__.py
arxiv_mcp/prompts/prompts.py
arxiv_mcp/resources/__init__.py
arxiv_mcp/resources/resources.py
arxiv_mcp/tools/__init__.py
arxiv_mcp/tools/tools.py
arxiv_paper_mcp-0.1.2.dist-info/METADATA
arxiv_paper_mcp-0.1.2.dist-info/WHEEL
arxiv_paper_mcp-0.1.2.dist-info/entry_points.txt
arxiv_paper_mcp-0.1.2.dist-info/top_level.txt
arxiv_paper_mcp-0.1.2.dist-info/RECORD
