Metadata-Version: 2.4
Name: arxiv-paper-mcp
Version: 0.1.2
Summary: arXiv 논문 데이터를 Claude AI와 연동하는 MCP 서버
Author-email: Park Dahee <dahee.pk@gmail.com>
Keywords: arxiv,claude,ai,research,papers
Requires-Python: >=3.11
Requires-Dist: mcp[cli]>=1.6.0
Requires-Dist: requests>=2.0.0
Requires-Dist: beautifulsoup4>=4.0.0
Requires-Dist: lxml>=4.0.0
